LICENSE
MANIFEST.in
README.md
package.json
setup.py
dash_ant_design_date_picker/DashAntDesignDatePicker.py
dash_ant_design_date_picker/__init__.py
dash_ant_design_date_picker/_imports_.py
dash_ant_design_date_picker/dash_ant_design_date_picker.min.js
dash_ant_design_date_picker/dash_ant_design_date_picker.min.js.map
dash_ant_design_date_picker/metadata.json
dash_ant_design_date_picker/package-info.json
dash_ant_design_date_picker.egg-info/PKG-INFO
dash_ant_design_date_picker.egg-info/SOURCES.txt
dash_ant_design_date_picker.egg-info/dependency_links.txt
dash_ant_design_date_picker.egg-info/top_level.txt