Metadata-Version: 1.1
Name: dash-ant-design-date-picker
Version: 0.0.1
Summary: Date range picker for Dash, based on Ant Design's RangePicker
Home-page: UNKNOWN
Author: Dennis Dieleman <dielemand@gmail.com>
Author-email: UNKNOWN
License: MIT
Platform: UNKNOWN
Classifier: Framework :: Dash
